aie4ml/__init__.py
aie4ml/_version.py
aie4ml/aie_backend.py
aie4ml/aie_devices.json
aie4ml/aie_types.py
aie4ml/device_catalog.py
aie4ml/kernel_registry.py
aie4ml/plugin.py
aie4ml/serialization.py
aie4ml/simulation.py
aie4ml/writer.py
aie4ml/ir/__init__.py
aie4ml/ir/context.py
aie4ml/ir/graph.py
aie4ml/passes/__init__.py
aie4ml/passes/fuse_activation.py
aie4ml/passes/lower.py
aie4ml/passes/memory_plan.py
aie4ml/passes/pack.py
aie4ml/passes/placement.py
aie4ml/passes/quant.py
aie4ml/passes/resolve.py
aie4ml/passes/resolve_registry.py
aie4ml/passes/utils.py
aie4ml/templates/firmware/Makefile.jinja
aie4ml/templates/firmware/aie.cfg.jinja
aie4ml/templates/firmware/app.cpp.jinja
aie4ml/templates/firmware/artifacts_1d.h.jinja
aie4ml/templates/firmware/artifacts_2d.h.jinja
aie4ml/templates/firmware/graph_plan.h.jinja
aie4ml/templates/firmware/parameters.h.jinja
aie4ml/templates/firmware/top_graph.h.jinja
aie4ml/templates/firmware/variants/dense_bias_relu/parameters.h.jinja
aie4ml/templates/nnet_utils/dense/dense.h
aie4ml/templates/nnet_utils/dense_bias_relu/dense_bias_relu.cpp
aie4ml/templates/nnet_utils/dense_bias_relu/dense_bias_relu.h
aie4ml/templates/nnet_utils/dense_bias_relu/dense_bias_relu_graph.h
aie4ml-0.1.2.dist-info/licenses/LICENSE
aie4ml-0.1.2.dist-info/METADATA
aie4ml-0.1.2.dist-info/WHEEL
aie4ml-0.1.2.dist-info/entry_points.txt
aie4ml-0.1.2.dist-info/top_level.txt
aie4ml-0.1.2.dist-info/RECORD
