Metadata-Version: 2.4
Name: aie4ml
Version: 0.1.2
Summary: AMD AIE backend plugin for hls4ml
Author-email: Dimitrios Danopoulos <dimitrios.danopoulos@cern.ch>
License:                                  Apache License
Project-URL: Homepage, https://github.com/dimdano/aie4ml
Project-URL: Issues, https://github.com/dimdano/aie4ml/issues
Keywords: hls4ml,aie,amd,fpga,backend,AI engine
Classifier: Development Status :: 3 - Alpha
Classifier: License :: OSI Approved :: Apache Software License
Classifier: Programming Language :: Python :: 3 :: Only
Requires-Python: >=3.10
License-File: LICENSE
Requires-Dist: jinja2>=3.0
Dynamic: license-file
